CODE_OF_CONDUCT.md
LICENSE
MANIFEST.in
README.md
requirements.txt
setup.cfg
setup.py
access_niu/__init__.py
access_niu/about.py
access_niu/app.py
access_niu/data.py
access_niu/infer.py
access_niu/persist.py
access_niu/pipeline.py
access_niu/train.py
access_niu/utility.py
access_niu/wsgi.py
access_niu.egg-info/PKG-INFO
access_niu.egg-info/SOURCES.txt
access_niu.egg-info/dependency_links.txt
access_niu.egg-info/requires.txt
access_niu.egg-info/top_level.txt
access_niu/components/__init__.py
access_niu/components/component.py
access_niu/components/classifiers/__init__.py
access_niu/components/classifiers/mobilenet_v2.py
access_niu/components/regressors/__init__.py
access_niu/components/regressors/mobilenet_v2.py
access_niu/tests/__init__.py
access_niu/tests/test_simple.py