Metadata-Version: 1.2
Name: access-niu
Version: 0.0.1
Summary: UNKNOWN
Home-page: UNKNOWN
Author: ConvexHull Technology Private Limited
Author-email: connect@accessai.co
Maintainer: Majeed Khan
Maintainer-email: majeed.khan@accessai.co
License: Apache 2.0
Platform: UNKNOWN
Classifier: Intended Audience :: Developers
Classifier: License :: OSI Approved :: Apache Software License
Classifier: Programming Language :: Python
Classifier: Programming Language :: Python :: 3.6
Classifier: Operating System :: OS Independent
Classifier: Topic :: Software Development :: Libraries
